LICENSE.txt
README.md
setup.py
morp/__init__.py
morp/__main__.py
morp/compat.py
morp/config.py
morp/exception.py
morp/message.py
morp.egg-info/PKG-INFO
morp.egg-info/SOURCES.txt
morp.egg-info/dependency_links.txt
morp.egg-info/entry_points.txt
morp.egg-info/requires.txt
morp.egg-info/top_level.txt
morp/interface/__init__.py
morp/interface/base.py
morp/interface/dropfile.py
morp/interface/sqs.py