Metadata-Version: 2.1
Name: morp
Version: 5.1.0
Summary: Send and receive messages without thinking about it
Home-page: http://github.com/Jaymon/morp
Author: Jay Marcyes
Author-email: jay@marcyes.com
License: MIT
Keywords: Amazon AWS SQS messages message-passing
Classifier: Development Status :: 4 - Beta
Classifier: Environment :: Web Environment
Classifier: Intended Audience :: Developers
Classifier: License :: OSI Approved :: MIT License
Classifier: Operating System :: OS Independent
Classifier: Topic :: Database
Classifier: Topic :: Software Development :: Libraries
Classifier: Topic :: Utilities
Classifier: Programming Language :: Python :: 3
License-File: LICENSE.txt
